discord_interactions/__init__.py
discord_interactions-0.2.0.dist-info/LICENSE
discord_interactions-0.2.0.dist-info/WHEEL
discord_interactions-0.2.0.dist-info/METADATA
discord_interactions-0.2.0.dist-info/RECORD
