Metadata-Version: 2.1
Name: discord-interactions
Version: 0.2.0
Summary: Useful tools for using the Discord Interactions API
Home-page: https://github.com/discord/discord-interactions-python
License: MIT
Keywords: discord
Author: Ian Webster
Author-email: ianw_pypi@ianww.com
Maintainer: Ian Webster
Maintainer-email: ianw_pypi@ianww.com
Requires-Python: >=3.6.0,<4.0.0
Classifier: License :: OSI Approved :: MIT License
Classifier: Programming Language :: Python :: 3
Classifier: Programming Language :: Python :: 3.6
Classifier: Programming Language :: Python :: 3.7
Classifier: Programming Language :: Python :: 3.8
Classifier: Programming Language :: Python :: 3.9
Requires-Dist: PyNaCl (>=1.4.0,<2.0.0)
Project-URL: Repository, https://github.com/discord/discord-interactions-python
